chrome_local_storage/__init__.py
chrome_local_storage-0.6.0.dist-info/LICENSE
chrome_local_storage-0.6.0.dist-info/WHEEL
chrome_local_storage-0.6.0.dist-info/METADATA
chrome_local_storage-0.6.0.dist-info/RECORD
