Metadata-Version: 2.1
Name: chrome-local-storage
Version: 0.6.0
Summary: Interact with Google Chrome local storage
Home-page: https://github.com/lordjabez/chrome-local-storage
License: MIT-0
Author: Judson Neer
Author-email: judson.neer@gmail.com
Requires-Python: >=3.7,<3.10
Classifier: License :: Other/Proprietary License
Classifier: Programming Language :: Python :: 3
Classifier: Programming Language :: Python :: 3.7
Classifier: Programming Language :: Python :: 3.8
Classifier: Programming Language :: Python :: 3.9
Requires-Dist: requests (>=2.25.0,<3.0.0)
Requires-Dist: trio-chrome-devtools-protocol (>=0.6.0,<0.7.0)
Project-URL: Repository, https://github.com/lordjabez/chrome-local-storage
